Metadata-Version: 2.1
Name: communebot-fr
Version: 0.0.3
Summary: A Twitter bot built with munibot that tweets aerial imagery pictures of France communes
Home-page: https://github.com/amercader/communebot_fr
Author: Adrià Mercader
Author-email: amercadero@gmail.com
License: UNKNOWN
Platform: UNKNOWN
Classifier: Programming Language :: Python :: 3
Classifier: License :: OSI Approved :: MIT License
Classifier: Operating System :: OS Independent
Requires-Python: >=3.6
